{
  "has_thumbnail": false, 
  "subsections": [
    {
      "has_thumbnail": true, 
      "name": "Chart Types", 
      "subsections": [
        {
          "parent": "chart-types", 
          "name": "Line and Scatter Plots", 
          "relative_url": "line-and-scatter", 
          "subsections": [
            {
              "code": "chart-types/line_and_scatter/gg-basic-line/ggplot2/code.txt", 
              "name": "Basic Line Chart", 
              "parent": "line_and_scatter", 
              "url": "https://plot.ly/~PlotBot/137", 
              "languages": [
                "ggplot2"
              ], 
              "id": "gg-basic-line"
            }, 
            {
              "code": "chart-types/line_and_scatter/gg-basic-scatter/ggplot2/code.txt", 
              "name": "Basic Scatter Plot", 
              "parent": "line_and_scatter", 
              "url": "https://plot.ly/~PlotBot/165", 
              "languages": [
                "ggplot2"
              ], 
              "id": "gg-basic-scatter"
            }, 
            {
              "code": "chart-types/line_and_scatter/gg-line-scatter/ggplot2/code.txt", 
              "name": "Line and Scatter Plot", 
              "parent": "line_and_scatter", 
              "url": "https://plot.ly/~PlotBot/138", 
              "languages": [
                "ggplot2"
              ], 
              "id": "gg-line-scatter"
            }, 
            {
              "code": "chart-types/line_and_scatter/gg-geom_point/ggplot2/code.txt", 
              "name": "<code>geom_point</code>", 
              "parent": "line_and_scatter", 
              "url": "https://plot.ly/~PlotBot/161", 
              "languages": [
                "ggplot2"
              ], 
              "id": "gg-geom_point"
            }, 
            {
              "code": "chart-types/line_and_scatter/gg-geom_segment/ggplot2/code.txt", 
              "name": "<code>geom_segment</code>", 
              "parent": "line_and_scatter", 
              "url": "https://plot.ly/~PlotBot/164", 
              "languages": [
                "ggplot2"
              ], 
              "id": "gg-geom_segment"
            }, 
            {
              "code": "chart-types/line_and_scatter/gg-geom_path/ggplot2/code.txt", 
              "name": "<code>geom_path</code>", 
              "parent": "line_and_scatter", 
              "url": "https://plot.ly/~PlotBot/163", 
              "languages": [
                "ggplot2"
              ], 
              "id": "gg-geom_path"
            }, 
            {
              "code": "chart-types/line_and_scatter/gg-geom_line/ggplot2/code.txt", 
              "name": "<code>geom_line</code>", 
              "parent": "line_and_scatter", 
              "url": "https://plot.ly/~PlotBot/166", 
              "languages": [
                "ggplot2"
              ], 
              "id": "gg-geom_line"
            }
          ], 
          "has_thumbnail": true, 
          "id": "line_and_scatter", 
          "description": "How to make line and scatter plots in {language}. {num_examples} examples of basic and colored line and scatter plots."
        }, 
        {
          "parent": "chart-types", 
          "name": "Bar Charts", 
          "relative_url": "bar-charts", 
          "subsections": [
            {
              "code": "chart-types/bar/gg-basic-bar/ggplot2/code.txt", 
              "name": "Basic Bar Chart", 
              "parent": "bar", 
              "url": "https://plot.ly/~PlotBot/139", 
              "languages": [
                "ggplot2"
              ], 
              "id": "gg-basic-bar"
            }
          ], 
          "has_thumbnail": true, 
          "id": "bar", 
          "description": "How to make a bar chart in {language}. {num_examples} examples of grouped, stacked, overlaid, and colored bar charts."
        }, 
        {
          "parent": "chart-types", 
          "name": "Line Shapes", 
          "relative_url": "line-shapes", 
          "subsections": [
            {
              "code": "chart-types/line_shapes/geom_step/ggplot2/code.txt", 
              "name": "<code>geom_step</code>", 
              "parent": "line_shapes", 
              "url": "https://plot.ly/~PlotBot/157", 
              "languages": [
                "ggplot2"
              ], 
              "id": "geom_step"
            }
          ], 
          "has_thumbnail": true, 
          "id": "line_shapes", 
          "description": "How to make line shapes in {language}."
        }, 
        {
          "parent": "chart-types", 
          "name": "Themes", 
          "relative_url": "themes", 
          "subsections": [
            {
              "code": "chart-types/gg-themes/few/ggplot2/code.txt", 
              "name": "<code>few</code> Theme", 
              "parent": "gg-themes", 
              "url": "https://plot.ly/~PlotBot/169", 
              "languages": [
                "ggplot2"
              ], 
              "id": "few"
            }, 
            {
              "code": "chart-types/gg-themes/igray/ggplot2/code.txt", 
              "name": "<code>igray</code> Theme", 
              "parent": "gg-themes", 
              "url": "https://plot.ly/~PlotBot/158", 
              "languages": [
                "ggplot2"
              ], 
              "id": "igray"
            }, 
            {
              "code": "chart-types/gg-themes/tableau/ggplot2/code.txt", 
              "name": "<code>Tableau</code> Theme", 
              "parent": "gg-themes", 
              "url": "https://plot.ly/~PlotBot/170", 
              "languages": [
                "ggplot2"
              ], 
              "id": "tableau"
            }
          ], 
          "has_thumbnail": true, 
          "id": "gg-themes", 
          "description": "How to apply ggplot2 themes to plots."
        }, 
        {
          "parent": "chart-types", 
          "name": "Functions", 
          "relative_url": "functions", 
          "subsections": [
            {
              "code": "chart-types/functions/x-squared/ggplot2/code.txt", 
              "name": "x<sup>2</sup>", 
              "parent": "functions", 
              "url": "https://plot.ly/~PlotBot/159", 
              "languages": [
                "ggplot2"
              ], 
              "id": "x-squared"
            }
          ], 
          "has_thumbnail": true, 
          "id": "functions", 
          "description": "How to plot functions in {language}."
        }, 
        {
          "parent": "chart-types", 
          "name": "Maps", 
          "relative_url": "maps", 
          "subsections": [
            {
              "code": "chart-types/maps/canadien-cities/ggplot2/code.txt", 
              "name": "Canadien Cities", 
              "parent": "maps", 
              "url": "https://plot.ly/~PlotBot/160", 
              "languages": [
                "ggplot2"
              ], 
              "id": "canadien-cities"
            }
          ], 
          "has_thumbnail": true, 
          "id": "maps", 
          "description": "How to visualize data with maps in {language}."
        }, 
        {
          "parent": "chart-types", 
          "name": "geom_polygon", 
          "relative_url": "geom_polygon", 
          "subsections": [
            {
              "code": "chart-types/geom_polygon/geom_polygon_1/ggplot2/code.txt", 
              "name": "geom_polygon", 
              "parent": "geom_polygon", 
              "url": "https://plot.ly/~PlotBot/168", 
              "languages": [
                "ggplot2"
              ], 
              "id": "geom_polygon_1"
            }
          ], 
          "has_thumbnail": true, 
          "id": "geom_polygon", 
          "description": "Examples of geom_polygon in R."
        }
      ], 
      "parent": "hard-coded", 
      "id": "chart-types"
    }, 
    {
      "has_thumbnail": false, 
      "name": "Interactive Embedding", 
      "subsections": [
        {
          "parent": "exlusive-embedding", 
          "name": "Embedding Graphs in HTML", 
          "relative_url": "embedding-plotly-graphs-in-HTML", 
          "subsections": [
            {
              "code": "exlusive-embedding/iframes-exlusive/iframes-exclusive/ggplot2/code.txt", 
              "name": "", 
              "parent": "iframes-exlusive", 
              "url": "https://plot.ly/~PlotBot/176", 
              "languages": [
                "ggplot2", 
                "matplotlib"
              ], 
              "id": "iframes-exclusive"
            }
          ], 
          "has_thumbnail": false, 
          "id": "iframes-exlusive", 
          "description": "How to embed plotly graphs with an iframe in HTML."
        }
      ], 
      "parent": "hard-coded", 
      "id": "exlusive-embedding"
    }
  ], 
  "name": "API Page for the people", 
  "id": "hard-coded"
}